python_watcher_metering_grid5000-0.22.0.data/data/etc/watcher-metering/watcher-metering-grid5000.conf.sample
python_watcher_metering_grid5000-0.22.0.data/data/etc/watcher-metering/agent.conf
python_watcher_metering_grid5000-0.22.0.dist-info/WHEEL
python_watcher_metering_grid5000-0.22.0.dist-info/pbr.json
python_watcher_metering_grid5000-0.22.0.dist-info/entry_points.txt
python_watcher_metering_grid5000-0.22.0.dist-info/metadata.json
python_watcher_metering_grid5000-0.22.0.dist-info/DESCRIPTION.rst
python_watcher_metering_grid5000-0.22.0.dist-info/top_level.txt
python_watcher_metering_grid5000-0.22.0.dist-info/RECORD
python_watcher_metering_grid5000-0.22.0.dist-info/METADATA
watcher_metering_grid5000/version.py
watcher_metering_grid5000/opts.py
watcher_metering_grid5000/base.py
watcher_metering_grid5000/doc.py
watcher_metering_grid5000/__init__.py
watcher_metering_grid5000/drivers.py
watcher_metering_grid5000/wrappers/__init__.py
watcher_metering_grid5000/wrappers/grid5000.py
watcher_metering_grid5000/tests/base.py
watcher_metering_grid5000/tests/test_grid5000_wrapper.py
watcher_metering_grid5000/tests/test_grid5000_register.py
watcher_metering_grid5000/tests/test_grid5000_base.py
watcher_metering_grid5000/tests/__init__.py
watcher_metering_grid5000/tests/_fixtures.py
watcher_metering_grid5000/tests/test_grid5000_drivers.py
watcher_metering_grid5000/tests/test_data/cpu_nice.json
watcher_metering_grid5000/tests/test_data/metadata.json
